starlark_go-1.0.0.dist-info/METADATA
starlark_go-1.0.0.dist-info/WHEEL
starlark_go-1.0.0.dist-info/RECORD
starlark_go-1.0.0.dist-info/top_level.txt
starlark_go-1.0.0.dist-info/LICENSE
starlark_go/scmversion.py
starlark_go/errors.py
starlark_go/py.typed
starlark_go/__init__.py
starlark_go/starlark_go.pyi
starlark_go/starlark_go.cpython-38-x86_64-linux-gnu.h
starlark_go/starlark_go.cpython-38-x86_64-linux-gnu.so
