Metadata-Version: 2.1
Name: starlark-go
Version: 1.0.0
Summary: Python bindings for the Go implementation of Starlark
Home-page: https://github.com/caketop/python-starlark-go
Author: Jordan Webb
Author-email: jordan@caketop.app
License: Apache License 2.0
Project-URL: Documentation, https://python-starlark-go.readthedocs.io/en/latest/
Project-URL: Bug Tracker, https://github.com/caketop/python-starlark-go/issues
Project-URL: Source Code, https://github.com/caketop/python-starlark-go
Keywords: starlark
Classifier: Development Status :: 4 - Beta
Classifier: Intended Audience :: Developers
Classifier: License :: OSI Approved :: Apache Software License
Classifier: Programming Language :: Python :: 3 :: Only
Classifier: Programming Language :: Python :: 3.7
Classifier: Programming Language :: Python :: 3.8
Classifier: Programming Language :: Python :: 3.9
Classifier: Programming Language :: Python :: 3.10
Classifier: Programming Language :: Python :: 3.11
Requires-Python: >=3.7
License-File: LICENSE
